pyfs_decrypt/__init__.py
pyfs_decrypt/data.py
pyfs_decrypt-1.0.0.dist-info/METADATA
pyfs_decrypt-1.0.0.dist-info/WHEEL
pyfs_decrypt-1.0.0.dist-info/top_level.txt
pyfs_decrypt-1.0.0.dist-info/RECORD
